<?xml version="1.0" encoding="UTF-8"?><factura id="comprobante" version="1.1.0"><infoTributaria><ambiente>1</ambiente><tipoEmision>1</tipoEmision><razonSocial>COOPERATIVA DE TRANSPORTES FLOTA PELILEO</razonSocial><nombreComercial>COOPERATIVA DE TRANSPORTES FLOTA PELILEO</nombreComercial><ruc>1890066123001</ruc><claveAcceso>0412202501189006612300120020030000000138436355011</claveAcceso><codDoc>01</codDoc><estab>000</estab><ptoEmi>001</ptoEmi><secuencial>000000013</secuencial><dirMatriz>Matriz Garcia Moreno y Montalvo</dirMatriz></infoTributaria><infoFactura><fechaEmision>04/12/2025</fechaEmision><dirEstablecimiento>Matriz Garcia Moreno y Montalvo</dirEstablecimiento><obligadoContabilidad>SI</obligadoContabilidad><tipoIdentificacionComprador>1</tipoIdentificacionComprador><razonSocialComprador>SAD</razonSocialComprador><identificacionComprador>0550203806001</identificacionComprador><direccionComprador>16 - 34</direccionComprador><totalSinImpuestos>0.00</totalSinImpuestos><totalDescuento>0.00</totalDescuento><totalConImpuestos><totalImpuesto><codigo>2</codigo><codigoPorcentaje>0</codigoPorcentaje><baseImponible>0.00</baseImponible><tarifa>0</tarifa><valor>0.00</valor></totalImpuesto><totalImpuesto><codigo>2</codigo><codigoPorcentaje>4</codigoPorcentaje><baseImponible>0.00</baseImponible><tarifa>15</tarifa><valor>0.00</valor></totalImpuesto></totalConImpuestos><propina>0.00</propina><importeTotal>1.00</importeTotal><moneda>DOLAR</moneda><pagos><pago><formaPago>01</formaPago><total>1.00</total></pago></pagos></infoFactura><detalles><detalle><codigoPrincipal>BOL.002</codigoPrincipal><codigoAuxiliar>BOL.002</codigoAuxiliar><descripcion>BOL.002 PRUBA VIAJE PRUBA-PRUBA 01Jan.1970 00 00 ASIENTO 3 PASAJERO SAD</descripcion><cantidad>1</cantidad><precioUnitario>1.00</precioUnitario><descuento>1.00</descuento><precioTotalSinImpuesto>1.00</precioTotalSinImpuesto><impuestos><impuesto><codigo>2</codigo><codigoPorcentaje>0</codigoPorcentaje><tarifa>0.00</tarifa><baseImponible>1.00</baseImponible><valor>1.00</valor></impuesto></impuestos></detalle></detalles></factura>